deta_base_pydantic/__init__.py
deta_base_pydantic-0.1.2.dist-info/LICENSE
deta_base_pydantic-0.1.2.dist-info/WHEEL
deta_base_pydantic-0.1.2.dist-info/METADATA
deta_base_pydantic-0.1.2.dist-info/RECORD
