Metadata-Version: 2.1
Name: deta_base_pydantic
Version: 0.1.2
Summary: A package providing a deta base interface for pydantic models.
Author-email: Panagiotis Karagiannis <papalotis1@gmail.com>
Classifier: License :: OSI Approved :: MIT License
Requires-Dist: pydantic
Requires-Dist: deta
Requires-Dist: fastapi
Project-URL: Home, https://github.com/papalotis/deta-base-pydantic
